{
	"backtrace" : 1,
	"backtraceGraph" : 
	{
		"commands" : 
		[
			"add_custom_target"
		],
		"files" : 
		[
			"/home/misys/forza_ws/race_stack/build/f110_msgs/f110_msgs__py/CMakeLists.txt"
		],
		"nodes" : 
		[
			{
				"file" : 0
			},
			{
				"command" : 0,
				"file" : 0,
				"line" : 34,
				"parent" : 0
			}
		]
	},
	"dependencies" : 
	[
		{
			"id" : "f110_msgs::@6890427a1f51a3e7e1df"
		}
	],
	"id" : "f110_msgs__py::@156c745a95625cbcbd3c",
	"name" : "f110_msgs__py",
	"paths" : 
	{
		"build" : "f110_msgs__py",
		"source" : "/home/misys/forza_ws/race_stack/build/f110_msgs/f110_msgs__py"
	},
	"sourceGroups" : 
	[
		{
			"name" : "",
			"sourceIndexes" : 
			[
				0
			]
		},
		{
			"name" : "CMake Rules",
			"sourceIndexes" : 
			[
				1,
				2
			]
		}
	],
	"sources" : 
	[
		{
			"backtrace" : 1,
			"isGenerated" : true,
			"path" : "/home/misys/forza_ws/race_stack/build/f110_msgs/f110_msgs__py/CMakeFiles/f110_msgs__py",
			"sourceGroupIndex" : 0
		},
		{
			"backtrace" : 0,
			"isGenerated" : true,
			"path" : "/home/misys/forza_ws/race_stack/build/f110_msgs/f110_msgs__py/CMakeFiles/f110_msgs__py.rule",
			"sourceGroupIndex" : 1
		},
		{
			"backtrace" : 0,
			"isGenerated" : true,
			"path" : "/home/misys/forza_ws/race_stack/build/f110_msgs/rosidl_generator_py/f110_msgs/_f110_msgs_s.ep.rosidl_typesupport_fastrtps_c.c.rule",
			"sourceGroupIndex" : 1
		}
	],
	"type" : "UTILITY"
}
